iwpc/__init__.py
iwpc/calculate_divergence.py
iwpc/logging_.py
iwpc/reweight_loop.py
iwpc/stat_utils.py
iwpc/types.py
iwpc/utils.py
iwpc/accumulators/Df_accumulator.py
iwpc/accumulators/__init__.py
iwpc/accumulators/binned_Df_accumulator.py
iwpc/accumulators/binned_stat_accumulator.py
iwpc/accumulators/binned_weighted_stat_accumulator.py
iwpc/accumulators/histogram_accumulator.py
iwpc/accumulators/utils.py
iwpc/callbacks/__init__.py
iwpc/data_modules/__init__.py
iwpc/data_modules/numpy_data_module.py
iwpc/data_modules/pandas_data_module.py
iwpc/data_modules/pandas_directory_data_module.py
iwpc/data_modules/pandas_directory_data_module_builder.py
iwpc/datasets/__init__.py
iwpc/datasets/pandas_dataset.py
iwpc/datasets/pandas_file_list_dataset.py
iwpc/datasets/pre_batched_dataset.py
iwpc/divergences/__init__.py
iwpc/divergences/base.py
iwpc/divergences/jensen_shannon_divergence.py
iwpc/divergences/kl_divergence.py
iwpc/encodings/__init__.py
iwpc/encodings/abs_encoding.py
iwpc/encodings/continuous_periodic_encoding.py
iwpc/encodings/encoding_base.py
iwpc/encodings/exponential_encoding.py
iwpc/encodings/log_encoding.py
iwpc/encodings/log_softmax_encoding.py
iwpc/encodings/matrix_encoding.py
iwpc/encodings/nope_encoding.py
iwpc/encodings/periodic_encoding.py
iwpc/encodings/reciprocal_encoding.py
iwpc/encodings/sign_encoding.py
iwpc/encodings/spherical_unit_vector_encoding.py
iwpc/encodings/trivial_encoding.py
iwpc/learn_dist/__init__.py
iwpc/learn_dist/classifier_reweighting.py
iwpc/learn_dist/base_distributions/__init__.py
iwpc/learn_dist/base_distributions/cauchy_base_model.py
iwpc/learn_dist/base_distributions/exponential_base_model.py
iwpc/learn_dist/base_distributions/histogram_base_model.py
iwpc/learn_dist/base_distributions/multivaraite_normal_base_model.py
iwpc/learn_dist/base_distributions/sampleable_base_model.py
iwpc/learn_dist/base_distributions/uniform_base_model.py
iwpc/learn_dist/kernels/AddCondKernel.py
iwpc/learn_dist/kernels/__init__.py
iwpc-0.7.5.dist-info/licenses/LICENSE
iwpc-0.7.5.dist-info/METADATA
iwpc-0.7.5.dist-info/WHEEL
iwpc-0.7.5.dist-info/top_level.txt
iwpc-0.7.5.dist-info/RECORD
