Metadata-Version: 2.4
Name: iwpc
Version: 0.7.5
Summary: An implementation of the divergence framework as described here https://arxiv.org/abs/2405.06397 and much more...
Author-email: "Jeremy J. H. Wilkinson" <jero.wilkinson@gmail.com>
Project-URL: Homepage, https://bitbucket.org/jjhw3/divergences/src/main/
Classifier: Development Status :: 3 - Alpha
Classifier: Programming Language :: Python :: 3
Classifier: License :: OSI Approved :: MIT License
Classifier: Operating System :: OS Independent
Requires-Python: >=3.9
License-File: LICENSE
Requires-Dist: numpy
Requires-Dist: torch
Requires-Dist: lightning
Requires-Dist: matplotlib
Requires-Dist: pandas
Requires-Dist: scikit-learn
Requires-Dist: tensorboard
Requires-Dist: seaborn
Requires-Dist: bokeh
Dynamic: license-file
